yorzoi/__init__.py
yorzoi/config.py
yorzoi/constants.py
yorzoi/dataset.py
yorzoi/loss.py
yorzoi/train.py
yorzoi/utils.py
yorzoi/model/__init__.py
yorzoi/model/attn_modules.py
yorzoi/model/baseline.py
yorzoi/model/borzoi.py
yorzoi/model/utils.py
yorzoi-0.0.3.dist-info/licenses/LICENSE.txt
yorzoi-0.0.3.dist-info/METADATA
yorzoi-0.0.3.dist-info/WHEEL
yorzoi-0.0.3.dist-info/top_level.txt
yorzoi-0.0.3.dist-info/RECORD
