Metadata-Version: 2.4
Name: yorzoi
Version: 0.0.3
Summary: Machine learning model that predicts RNA-seq coverage from DNA
Home-page: https://github.com/Tom-Ellis-Lab/yorzoi
Author: Timon Schneider
Author-email: mail@timonschneider.de
License-File: LICENSE.txt
Requires-Dist: packaging
Requires-Dist: ninja
Requires-Dist: einops>=0.5
Requires-Dist: matplotlib
Requires-Dist: pandas
Requires-Dist: torch>=2.1.0
Requires-Dist: wandb
Requires-Dist: transformers>=4.34.1
Requires-Dist: numpy>=1.14.2
Dynamic: license-file
